LICENSE
MANIFEST.in
README.md
setup.cfg
setup.py
stogui/__init__.py
stogui.egg-info/PKG-INFO
stogui.egg-info/SOURCES.txt
stogui.egg-info/dependency_links.txt
stogui.egg-info/not-zip-safe
stogui.egg-info/requires.txt
stogui.egg-info/top_level.txt
stogui/dpp_table/__init__.py
stogui/dpp_table/frontend/build/asset-manifest.json
stogui/dpp_table/frontend/build/bootstrap.min.css
stogui/dpp_table/frontend/build/index.html
stogui/dpp_table/frontend/build/precache-manifest.8768e2576ba32fb16e6269cdf3a0f322.js
stogui/dpp_table/frontend/build/service-worker.js
stogui/dpp_table/frontend/build/static/js/2.67e2698d.chunk.js
stogui/dpp_table/frontend/build/static/js/2.67e2698d.chunk.js.LICENSE.txt
stogui/dpp_table/frontend/build/static/js/2.67e2698d.chunk.js.map
stogui/dpp_table/frontend/build/static/js/main.5d6c9b4e.chunk.js
stogui/dpp_table/frontend/build/static/js/main.5d6c9b4e.chunk.js.map
stogui/dpp_table/frontend/build/static/js/runtime-main.44d30fc2.js
stogui/dpp_table/frontend/build/static/js/runtime-main.44d30fc2.js.map
stogui/drag_and_drop_flow/__init__.py
stogui/drag_and_drop_flow/frontend/build/asset-manifest.json
stogui/drag_and_drop_flow/frontend/build/bootstrap.min.css
stogui/drag_and_drop_flow/frontend/build/index.html
stogui/drag_and_drop_flow/frontend/build/precache-manifest.b0b8921a2b52f016e9e3f6ff56ac860b.js
stogui/drag_and_drop_flow/frontend/build/service-worker.js
stogui/drag_and_drop_flow/frontend/build/static/js/2.9ce70f94.chunk.js
stogui/drag_and_drop_flow/frontend/build/static/js/2.9ce70f94.chunk.js.LICENSE.txt
stogui/drag_and_drop_flow/frontend/build/static/js/2.9ce70f94.chunk.js.map
stogui/drag_and_drop_flow/frontend/build/static/js/main.8509ceb3.chunk.js
stogui/drag_and_drop_flow/frontend/build/static/js/main.8509ceb3.chunk.js.map
stogui/drag_and_drop_flow/frontend/build/static/js/runtime-main.44d30fc2.js
stogui/drag_and_drop_flow/frontend/build/static/js/runtime-main.44d30fc2.js.map
stogui/pipeline_maker/__init__.py
stogui/pipeline_maker/frontend/build/asset-manifest.json
stogui/pipeline_maker/frontend/build/bootstrap.min.css
stogui/pipeline_maker/frontend/build/index.html
