Metadata-Version: 2.1
Name: stogui
Version: 0.1.13
Summary: There is a bit of an air of mystery around this project...
Home-page: UNKNOWN
License: mit
Platform: UNKNOWN
